st_copy/__init__.py
st_copy/py.typed
st_copy/frontend/dist/index.html
st_copy/frontend/dist/assets/index-C77nLE-4.js
st_copy-1.1.1.dist-info/METADATA
st_copy-1.1.1.dist-info/WHEEL
st_copy-1.1.1.dist-info/licenses/LICENSE
st_copy-1.1.1.dist-info/RECORD
