Metadata-Version: 2.4
Name: st-copy
Version: 1.1.1
Summary: Streamlit copy‑to‑clipboard button component
Author-email: Aleksandr Filippov <alex-feel.saga628@passmail.com>
License-File: LICENSE
Requires-Python: >=3.9
Requires-Dist: streamlit>=0.79.0
